dict_converter/__init__.py
dict_converter-0.1.2.dist-info/METADATA
dict_converter-0.1.2.dist-info/WHEEL
dict_converter-0.1.2.dist-info/top_level.txt
dict_converter-0.1.2.dist-info/RECORD
