Metadata-Version: 2.1
Name: dict-converter
Version: 0.1.2
Summary: A chain-line dict converter in Python 3
Home-page: https://duyixian1234.visualstudio.com/dict-converter
Author: Yixian Du
Author-email: duyixian1234@qq.com
License: MIT
Platform: UNKNOWN
Classifier: License :: OSI Approved :: MIT License
Classifier: Programming Language :: Python
Classifier: Programming Language :: Python :: 3.6
Classifier: Programming Language :: Python :: 3.7
Classifier: Programming Language :: Python :: Implementation :: CPython
